<?xml version="1.0" encoding="UTF-8"?>
<!DOCTYPE configuration 
PUBLIC "-//mybatis.org//DTD Config 3.0//EN"
"http://mybatis.org/dtd/mybatis-3-config.dtd">

 <configuration>
	<typeAliases>
  		<typeAlias type="com.movie.damovie.member.vo.MemberVO" alias="memberVO"/>
  		<typeAlias type="com.movie.damovie.book.bookForm.VO.MovieTimeVO" alias="movieTimeVO"/>
  		<typeAlias type="com.movie.damovie.book.order.VO.OrderVO" alias="orderVO"/>
  		<typeAlias type="com.movie.damovie.customer.vo.CustomerMovieVO" alias="customerMovieVO"/>
  		<typeAlias type="com.movie.damovie.customer.vo.CustomerTheaterVO" alias="customerTheaterVO"/>
  		<typeAlias type="com.movie.damovie.customer.vo.CustomerSeatVO" alias="customerSeatVO"/>
  		<typeAlias alias="reviewVO" type="com.movie.damovie.review.reviewForm.vo.ReviewVO"/>
  		<typeAlias alias="writeVO" type="com.movie.damovie.review.reviewForm.vo.WriteVO"/>
  		<typeAlias type="com.movie.damovie.customer.vo.CustomerSeatValueVO" alias="customerSeatValueVI"/> 
	</typeAliases>
</configuration>